{
  "dashboard": {
    "id": null,
    "title": "Audio Monitoring Dashboard",
    "panels": [
      {
        "type": "graph",
        "title": "Latency (ms)",
        "targets": [
          {
            "expr": "latency_ms",
            "legendFormat": "Latency"
          }
        ]
      },
      {
        "type": "graph",
        "title": "Requests Total",
        "targets": [
          {
            "expr": "requests_total",
            "legendFormat": "Requests"
          }
        ]
      },
      {
        "type": "graph",
        "title": "Errors Total",
        "targets": [
          {
            "expr": "errors_total",
            "legendFormat": "Errors"
          }
        ]
      }
    ]
  }
}

